bmatrix/__init__.py
bmatrix/bmatrix.py
bmatrix/bmatrix_cart.py
bmatrix/datastruct.py
bmatrix/dealxyz.py
bmatrix/inputparser.py
bmatrix/intcoord.py
bmatrix/physconstants.py
bmatrix/readandwrite.py
bmatrix/various.py
bmatrix-1.0.1.dist-info/COPYING
bmatrix-1.0.1.dist-info/WHEEL
bmatrix-1.0.1.dist-info/METADATA
bmatrix-1.0.1.dist-info/RECORD
