Metadata-Version: 2.1
Name: bmatrix
Version: 1.0.1
Summary: Package with tools for generating internal coordiantes and the corresponding B matrix for molecules and for periodic systems.
Home-page: https://github.com/lmmentel/bmatrix
License: GNU
Keywords: coordinates,internal,molecules,geometry,solids
Author: Lukasz Mentel
Author-email: lmmentel@gmail.com
Maintainer: Lukasz Mentel
Maintainer-email: lmmentel@gmail.com
Requires-Python: >=3.8,<3.10
Classifier: License :: Other/Proprietary License
Classifier: Programming Language :: Python :: 3
Classifier: Programming Language :: Python :: 3.8
Classifier: Programming Language :: Python :: 3.9
Requires-Dist: numpy (>=1.21.1,<2.0.0)
Requires-Dist: scipy (>=1.7.1,<2.0.0)
Project-URL: Repository, https://github.com/lmmentel/bmatrix
